iamdata/__init__.py
iamdata/actions.py
iamdata/conditions.py
iamdata/resources.py
iamdata/services.py
iamdata/utils.py
iamdata/data/conditionPatterns.json
iamdata/data/metadata.json
iamdata/data/serviceNames.json
iamdata/data/services.json
iamdata/data/unassociatedConditions.json
iamdata/data/actions/a2c.json
iamdata/data/actions/a4b.json
iamdata/data/actions/access-analyzer.json
iamdata/data/actions/account.json
iamdata/data/actions/acm-pca.json
iamdata/data/actions/acm.json
iamdata/data/actions/aco-automation.json
iamdata/data/actions/action-recommendations.json
iamdata/data/actions/activate.json
iamdata/data/actions/aidevops.json
iamdata/data/actions/aiops.json
iamdata/data/actions/airflow-serverless.json
iamdata/data/actions/airflow.json
iamdata/data/actions/amplify.json
iamdata/data/actions/amplifybackend.json
iamdata/data/actions/amplifyuibuilder.json
iamdata/data/actions/aoss.json
iamdata/data/actions/apigateway.json
iamdata/data/actions/app-integrations.json
iamdata/data/actions/appconfig.json
iamdata/data/actions/appfabric.json
iamdata/data/actions/appflow.json
iamdata/data/actions/application-autoscaling.json
iamdata/data/actions/application-signals.json
iamdata/data/actions/application-transformation.json
iamdata/data/actions/applicationinsights.json
iamdata/data/actions/appmesh-preview.json
iamdata/data/actions/appmesh.json
iamdata/data/actions/apprunner.json
iamdata/data/actions/appstream.json
iamdata/data/actions/appstudio.json
iamdata/data/actions/appsync.json
iamdata/data/actions/apptest.json
iamdata/data/actions/aps.json
iamdata/data/actions/arc-region-switch.json
iamdata/data/actions/arc-zonal-shift.json
iamdata/data/actions/arsenal.json
iamdata/data/actions/artifact.json
iamdata/data/actions/athena.json
iamdata/data/actions/auditmanager.json
iamdata/data/actions/autoscaling-plans.json
iamdata/data/actions/autoscaling.json
iamdata/data/actions/aws-marketplace-management.json
iamdata/data/actions/aws-marketplace.json
iamdata-0.1.202602011.dist-info/METADATA
iamdata-0.1.202602011.dist-info/WHEEL
iamdata-0.1.202602011.dist-info/licenses/LICENSE.txt
iamdata-0.1.202602011.dist-info/RECORD
