Metadata-Version: 2.4
Name: iamdata
Version: 0.1.202602011
Summary: IAM data for AWS actions, resources, and conditions based on IAM policy documents. Checked for updates daily.
Project-URL: Homepage, https://github.com/cloud-copilot/iam-data-python
Project-URL: Issues, https://github.com/cloud-copilot/iam-data-python/issues
Author-email: David Kerber <dave@cloudcopilot.io>
License-File: LICENSE.txt
Classifier: License :: OSI Approved :: MIT License
Classifier: Operating System :: OS Independent
Classifier: Programming Language :: Python :: 3
Requires-Python: >=3.7
